[
  {
    "name": "dpr",
    "value": "1.5",
    "domain": ".facebook.com",
    "path": "/",
    "expires": 1776081196,
    "size": 6,
    "httpOnly": false,
    "secure": true,
    "session": false,
    "sameSite": "None",
    "priority": "Medium",
    "sourceScheme": "Secure",
    "sameParty": false
  },
  {
    "name": "datr",
    "value": "5ZrTacMS80rAHJ72sBiz4Lok",
    "domain": ".facebook.com",
    "path": "/",
    "expires": 1810035429.8666,
    "size": 28,
    "httpOnly": true,
    "secure": true,
    "session": false,
    "sameSite": "None",
    "priority": "Medium",
    "sourceScheme": "Secure",
    "sameParty": false
  },
  {
    "name": "wd",
    "value": "1280x665",
    "domain": ".facebook.com",
    "path": "/",
    "expires": 1776081196,
    "size": 10,
    "httpOnly": false,
    "secure": true,
    "session": false,
    "sameSite": "Lax",
    "priority": "Medium",
    "sourceScheme": "Secure",
    "sameParty": false
  },
  {
    "name": "sb",
    "value": "5ZrTabzzgvjsEgSQVwpRc_NP",
    "domain": ".facebook.com",
    "path": "/",
    "expires": 1810035501.698883,
    "size": 26,
    "httpOnly": true,
    "secure": true,
    "session": false,
    "sameSite": "None",
    "priority": "Medium",
    "sourceScheme": "Secure",
    "sameParty": false
  },
  {
    "name": "fr",
    "value": "1vqzY5DngSJHlyK3t.AWc5MvmaIB2c3UpgcjQJ3tMYZZwHnr5vJDnBASTa_iHmdZjtyOE.Bp05yW..AAA.0.0.Bp05yW.AWdaD_mvw3n0a0oy-iS6pIVZcrg",
    "domain": ".facebook.com",
    "path": "/",
    "expires": 1783251863.261627,
    "size": 122,
    "httpOnly": true,
    "secure": true,
    "session": false,
    "sameSite": "None",
    "priority": "Medium",
    "sourceScheme": "Secure",
    "sameParty": false
  },
  {
    "name": "xs",
    "value": "38%3AptZnZONrDeK90Q%3A2%3A1775475499%3A-1%3A-1%3A%3AAcyStXACOFxLv_4J4kSzlIAWNllOUXKYRyuYod0bJw",
    "domain": ".facebook.com",
    "path": "/",
    "expires": 1807011863.261669,
    "size": 96,
    "httpOnly": true,
    "secure": true,
    "session": false,
    "sameSite": "None",
    "priority": "Medium",
    "sourceScheme": "Secure",
    "sameParty": false
  },
  {
    "name": "c_user",
    "value": "61575054939020",
    "domain": ".facebook.com",
    "path": "/",
    "expires": 1807011863.261545,
    "size": 20,
    "httpOnly": false,
    "secure": true,
    "session": false,
    "sameSite": "None",
    "priority": "Medium",
    "sourceScheme": "Secure",
    "sameParty": false
  },
  {
    "name": "presence",
    "value": "C%7B%22t3%22%3A%5B%5D%2C%22utc3%22%3A1775476396329%2C%22v%22%3A1%7D",
    "domain": ".facebook.com",
    "path": "/",
    "expires": -1,
    "size": 75,
    "httpOnly": false,
    "secure": true,
    "session": true,
    "priority": "Medium",
    "sourceScheme": "Secure",
    "sameParty": false
  }
]